Metadata-Version: 1.0
Name: distribution-gb
Version: 1.0
Summary: Gaussian and Binomial Distribution
Home-page: UNKNOWN
Author: Anurag Borah
Author-email: anuragborah2548@gmail.com
License: UNKNOWN
Platform: UNKNOWN
